pytxc/__init__.py
pytxc/datasets.py
pytxc/elements.py
pytxc/journeys.py
pytxc/links.py
pytxc/operators.py
pytxc/routes.py
pytxc/services.py
pytxc/stops.py
pytxc/timetables.py
pytxc/vehicles.py
pytxc-0.1.6.dist-info/WHEEL
pytxc-0.1.6.dist-info/METADATA
pytxc-0.1.6.dist-info/RECORD
